Metadata-Version: 2.1
Name: example-pkg-berry0303
Version: 0.0.1
Summary: A small example package
Home-page: https://github.com/pypa/sampleproject
Author: berry0303
Author-email: berry_0403@163.com
Classifier: Programming Language :: Python :: 3
Classifier: License :: OSI Approved :: MIT License
Classifier: Operating System :: OS Independent
License-File: LICENSE
Requires-Dist: pandas>=1.3.5
